simpcap/__init__.py
simpcap-1.0.0.dist-info/DESCRIPTION.rst
simpcap-1.0.0.dist-info/METADATA
simpcap-1.0.0.dist-info/RECORD
simpcap-1.0.0.dist-info/WHEEL
simpcap-1.0.0.dist-info/entry_points.txt
simpcap-1.0.0.dist-info/metadata.json
simpcap-1.0.0.dist-info/top_level.txt
